Workbook

Sheet Leeme
A1: SuiteHub · Catálogo de precios 2026 — mesa de revisión
A2: Consolidado de TODAS las fuentes de precio que existen hoy (panel, sitio, docs, estudio de mercado, modelo de mayo) para revisar y decidir en un solo lugar.
A3: Generado 2026-09-06 · Base de trabajo: C:\xampp\htdocs\_suitehub-brand\catalogo\
A5: Parámetros
A6: Factor anual (anual = mensual × factor) | C6: 10
A7: Descuento anual equivalente | C7: =1-C6/12 -> 0.16666667
A8: Moneda | C8: USD (Balboa a la par)
A9: Entidad Panamá | C9: PROOQ S.A. — base de operaciones Panamá
A10: Entidad USA | C10: PROOQ LLC — base de operaciones EE.UU.
A12: Deltas de módulo adicional ($/mes, uso futuro)
A13: Grupo | C13: $/mes
A14: ligero | C14: 12
A15: medio | C15: 24
A16: pesado | C16: 36
A18: Jerarquía de fuentes (de más a menos autoritativa hoy)
A19: # | B19: Fuente | C19: Qué es / dónde vive
A20: 1 | B20: Panel en vivo | C20: panel.suitehub.net → Catalog.php defaults() + overrides en BD (catalog_versions). Export público /?r=catalog/json. Es lo que ve el cliente en landings y correos.
A21: 2 | B21: JSON del sitio | C21: suitehub/src/data/catalogo.json (copia del export, 2026-08-02). Alimenta suitehub.net/precios en build.
A22: 3 | B22: CATALOGO.md | C22: suitehub/CATALOGO.md (2026-06-25). Documento humano del modelo de ediciones. Puede ir por detrás del panel.
A23: 4 | B23: Products.php | C23: panel/src/Products.php. Solo trae precio para productos SIN contraparte en catálogo: pos, market, boutique.
A24: 5 | B24: PRODUCTS.md (brand) | C24: _suitehub-brand/PRODUCTS.md (2026-05-22). Estado de productos y colores; no es fuente de precio.
A25: 6 | B25: Estudio de mercado jun-2026 | C25: _suitehub-brand/estudio-mercado-2026/SuiteHub-Precios-Panama-2026.xlsx. Modelo ANTERIOR: 3 planes por producto + setup one-time.
A26: 7 | B26: Modelo mayo-2026 (memoria) | C26: Puntos a $12/pt y precios de restaurante con pago inicial (Kiosko $1,500+$59/mes, POS $3,800+$149, Restaurante $5,500+$249). Modelo de licencia, previo al de suscripción.
A28: Leyenda
A29: Texto azul | C29: Valor de entrada, editable.
A30: Texto negro | C30: Fórmula, no tocar.
A31: Texto verde | C31: Fórmula que lee otra hoja.
A32: Fondo amarillo | C32: Decisión pendiente de Kenny. Llena la columna 'Decisión'.
A33: Fondo rojo | C33: Conflicto entre fuentes: dos números distintos para lo mismo.
A35: Flujo propuesto: se decide aquí → se aplica en el panel (?r=catalog/edit) → el panel exporta JSON → el sitio lo consume. Este archivo NO alimenta nada automáticamente: es la mesa de decisión.

Sheet Ediciones
A1: Eje horizontal — Ediciones (precio de lista)
A2: Fuente: Catalog.php defaults() + JSON vivo 2026-08-02. $/año = $/mes × factor (Leeme!C6).
A4: key | B4: Edición | C4: $/mes | D4: $/año | E4: Sucursales | F4: Usuarios | G4: Registros | H4: Almacenamiento | I4: Transac./mes | J4: Salto clave | K4: Estado | L4: Fuente | M4: Decisión / nota
A5: lite | B5: Lite | C5: 24 | D5: =C5*Leeme!$C$6 -> 240 | E5: 1 | F5: 3 | G5: 500 | H5: 2 GB | I5: 100 | J5: Lo básico con FE DGI incluida: clientes, catálogo, cotizaciones y facturación electrónica. | K5: confirmado | L5: Catalog.php + JSON
A6: core | B6: Core ⭐ | C6: 48 | D6: =C6*Leeme!$C$6 -> 480 | E6: 1 | F6: 8 | G6: 5,000 | H6: 10 GB | I6: 1,000 | J6: Activa FE DGI (Digifact/HKA/Factura Fácil/eFacturapty), CxC multi-factura, reportes SQL y plantillas PDF. | K6: confirmado | L6: Catalog.php + JSON
A7: pro | B7: Pro | C7: 96 | D7: =C7*Leeme!$C$6 -> 960 | E7: 2 | F7: 20 | G7: 50,000 | H7: 50 GB | I7: 10,000 | J7: Multi-sucursal real, automatizaciones, API REST (100K/mes), webhooks, WhatsApp Business, branding propio. | K7: confirmado | L7: Catalog.php + JSON
A8: enterprise | B8: Enterprise | C8: 192 | D8: =C8*Leeme!$C$6 -> 1920 | E8: 3 | F8: 50 | G8: Ilimitados | H8: 200 GB | I8: Ilimitadas | J8: White-label completo (revender), reportes con IA, API ilimitada, SLA, account manager, integraciones custom. | K8: confirmado (sucursales: override) | L8: JSON vivo; Catalog.php dice 'Ilimitadas' | M8: CONFLICTO: código dice sucursales ilimitadas; panel en vivo cobra +$64 por adicional. ¿Cuál queda?
A10: Lite incluye FE DGI (CATALOGO.md y JSON coinciden). Nota: el estudio de junio y PRODUCTS.md describen 'Lite' con otros alcances — ver Conflictos #3.

Sheet Verticales
A1: Eje vertical — Verticales en línea de edición
A2: Regla: el vertical toma el precio de la edición, sin recargo, salvo 'precio propio' que reemplaza SOLO la columna de su edición mínima. '—' = no se vende en esa edición. Delta = módulo adicional (uso futuro, no se suma).
A4: key | B4: Vertical | C4: Sector | D4: Grupo | E4: Ed. mínima | F4: Precio propio $/mes | G4: Lite $/mes | H4: Core $/mes | I4: Pro $/mes | J4: Enterprise $/mes | K4: $/año en ed. mínima | L4: Delta módulo $/mes | M4: Caso real | N4: En Catalog.php (código) | O4: En JSON vivo (panel) | P4: Badge SVG | Q4: Logo SVG | R4: Fuente | S4: Decisión / nota
A5: taller | B5: HUB Taller | C5: Talleres mecánicos | D5: medio | E5: Lite | F5: 48 | G5: 48 | H5: 64 | I5: eliminado por ahora | J5: Nada | K5: =IFERROR(INDEX(G5:J5,MATCH($E5,Ediciones!$A$5:$A$8,0))*Leeme!$C$6,"") -> 480 | L5: Sin Delta | M5: QS Express — La Chorrera | N5: sí | O5: sí | P5: sí | Q5: sí | R5: Catalog.php
A6: carwash | B6: HUB Carwash | C6: Autolavados | D6: medio | E6: Lite | F6: 48 | G6: 48 | H6: 64 | I6: eliminado por ahora | J6: Nada | K6: =IFERROR(INDEX(G6:J6,MATCH($E6,Ediciones!$A$5:$A$8,0))*Leeme!$C$6,"") -> 480 | L6: Sin Delta | N6: sí | O6: sí | P6: sí | Q6: sí | R6: Catalog.php | S6: Lanzamiento $24 (PANEL-SUITEHUB.md) ya reconciliado a $48 el 2026-05-30.
A7: restaurant | B7: HUB Restaurant | C7: Restaurantes y bares | D7: pesado | E7: Lite | F7: 48 | G7: 48 | H7: 64 | I7: eliminado por ahora | J7: Nada | K7: =IFERROR(INDEX(G7:J7,MATCH($E7,Ediciones!$A$5:$A$8,0))*Leeme!$C$6,"") -> 480 | L7: Sin Delta | N7: sí (precio null) | O7: sí ($72 Core) | P7: sí | Q7: sí | R7: Override en BD del panel | S7: CONFLICTO: código = $48 (línea Core); panel en vivo = $72. Si se pierde la BD vuelve a $48. ¿Confirmar $72 y llevarlo a código?
A8: pet | B8: HUB Pet | C8: Veterinarias y pet shops | D8: medio | E8: Lite | F8: 48 | G8: 48 | H8: 64 | I8: eliminado por ahora | J8: Nada | K8: =IFERROR(INDEX(G8:J8,MATCH($E8,Ediciones!$A$5:$A$8,0))*Leeme!$C$6,"") -> 480 | L8: Sin Delta | N8: sí | O8: sí | P8: sí | Q8: sí | R8: Catalog.php | S8: Precio propio $36 sobre línea Lite $24.
A9: beauty | B9: HUB Beauty | C9: Salones, spas, barberías | D9: ligero | E9: Lite | F9: 48 | G9: 48 | H9: 64 | I9: eliminado por ahora | J9: Nada | K9: =IFERROR(INDEX(G9:J9,MATCH($E9,Ediciones!$A$5:$A$8,0))*Leeme!$C$6,"") -> 480 | L9: Sin Delta | N9: sí | O9: sí | P9: sí (beauty) | Q9: no (hay hub-salon-logo) | R9: Catalog.php | S9: Renombre Beauty→Salon a medias: catálogo dice Beauty, brand kit tiene logo Salon. ¿Nombre final?
A10: clinic | B10: HUB Clinic | C10: Consultorios y clínicas | D10: medio | E10: Lite | F10: 48 | G10: 48 | H10: 64 | I10: eliminado por ahora | J10: Nada | K10: =IFERROR(INDEX(G10:J10,MATCH($E10,Ediciones!$A$5:$A$8,0))*Leeme!$C$6,"") -> 480 | L10: Sin Delta | N10: sí | O10: sí | P10: sí | Q10: sí | R10: Catalog.php
A11: gym | B11: HUB Gym | C11: Gimnasios, crossfit, yoga | D11: medio | E11: Lite | F11: 48 | G11: 48 | H11: 64 | I11: eliminado por ahora | J11: Nada | K11: =IFERROR(INDEX(G11:J11,MATCH($E11,Ediciones!$A$5:$A$8,0))*Leeme!$C$6,"") -> 480 | L11: Sin Delta | N11: sí | O11: sí | P11: sí | Q11: sí | R11: Catalog.php
A12: lavanderia | B12: HUB Lavandería | C12: Lavanderías | D12: ligero | E12: Lite | F12: 48 | G12: 48 | H12: 64 | I12: eliminado por ahora | J12: Nada | K12: =IFERROR(INDEX(G12:J12,MATCH($E12,Ediciones!$A$5:$A$8,0))*Leeme!$C$6,"") -> 480 | L12: Sin Delta | M12: Clean Factory — Panamá | N12: sí | O12: sí | P12: sí | Q12: sí | R12: Catalog.php
A13: inmobiliaria | B13: HUB Inmobiliaria | C13: Bienes raíces | D13: ligero | E13: Lite | F13: 48 | G13: 48 | H13: 64 | I13: eliminado por ahora | J13: Nada | K13: =IFERROR(INDEX(G13:J13,MATCH($E13,Ediciones!$A$5:$A$8,0))*Leeme!$C$6,"") -> 480 | L13: Sin Delta | N13: sí | O13: sí | P13: sí | Q13: sí | R13: Catalog.php
A14: hotel | B14: HUB Hotel | C14: Hoteles boutique y hostales | D14: medio | E14: Lite | F14: 48 | G14: 48 | H14: 64 | I14: eliminado por ahora | J14: Nada | K14: =IFERROR(INDEX(G14:J14,MATCH($E14,Ediciones!$A$5:$A$8,0))*Leeme!$C$6,"") -> 480 | L14: Sin Delta | N14: sí | O14: sí | P14: sí | Q14: sí | R14: Catalog.php
A15: phone | B15: HUB Phone | C15: Reparación de celulares | D15: ligero | E15: Lite | F15: 48 | G15: 48 | H15: 64 | I15: eliminado por ahora | J15: Nada | K15: =IFERROR(INDEX(G15:J15,MATCH($E15,Ediciones!$A$5:$A$8,0))*Leeme!$C$6,"") -> 480 | L15: Sin Delta | N15: sí | O15: sí | P15: sí | Q15: sí | R15: Catalog.php
A16: traffic | B16: HUB Traffic | C16: Analítica de afluencia retail | D16: pesado | E16: Lite | F16: 48 | G16: 48 | H16: 64 | I16: eliminado por ahora | J16: Nada | K16: =IFERROR(INDEX(G16:J16,MATCH($E16,Ediciones!$A$5:$A$8,0))*Leeme!$C$6,"") -> 480 | L16: Sin Delta | N16: sí | O16: sí | P16: sí | Q16: sí | R16: Catalog.php (delta: propuesta) | S16: Suma setup de hardware (cotización). Delta +$30 propuesto sin confirmar.
A17: boutique | B17: HUB Boutique | C17: Boutiques de ropa, retail premium | E17: Lite | F17: 48 | G17: 48 | H17: 64 | I17: eliminado por ahora | J17: Nada | K17: =IFERROR(INDEX(G17:J17,MATCH($E17,Ediciones!$A$5:$A$8,0))*Leeme!$C$6,"") -> 480 | L17: Sin Delta | N17: NO (solo override BD) | O17: sí ($48) | P17: no | Q17: no | R17: Override en BD + Products.php $48 | S17: Producto insignia según plan 2026, pero sin badge, sin logo y fuera del código. ¿Grupo? ¿Se queda a $48?
A18: market | B18: HUB Market | C18: Minimarkets | E18: Lite | F18: 48 | G18: 48 | H18: 64 | I18: eliminado por ahora | J18: Nada | K18: =IFERROR(INDEX(G18:J18,MATCH($E18,Ediciones!$A$5:$A$8,0))*Leeme!$C$6,"") -> 480 | L18: Sin Delta | N18: NO (solo override BD) | O18: sí ($48) | P18: no | Q18: no | R18: Override en BD + Products.php $48 | S18: Sin grupo, sin badge ni logo en brand kit. ¿Grupo?
A19: pos | B19: HUB POS | C19: Caja / punto de venta | E19: Lite | F19: 48 | G19: 48 | H19: 64 | I19: eliminado por ahora | J19: Nada | K19: =IFERROR(INDEX(G19:J19,MATCH($E19,Ediciones!$A$5:$A$8,0))*Leeme!$C$6,"") -> 480 | L19: Sin Delta | N19: NO (producto, no vertical) | O19: no | P19: sí | Q19: sí | R19: Products.php $48 · CATALOGO.md $36 | S19: CONFLICTO: ver Especiales #1. ¿Es vertical o producto standalone?
A20: time | B20: HUB Time | C20: (por definir) | E20: Lite | F20: 48 | G20: 48 | H20: 64 | I20: eliminado por ahora | J20: Nada | K20: =IFERROR(INDEX(G20:J20,MATCH($E20,Ediciones!$A$5:$A$8,0))*Leeme!$C$6,"") -> 480 | L20: Sin Delta | N20: no | O20: no | P20: sí | Q20: sí | R20: Brand kit ago-2026 | S20: Existe en brand kit (badge, logo, favicons, preview) pero no en catálogo. ¿Qué es, qué precio, qué edición mínima?
A21: salon | B21: HUB Salon | C21: Salones / barberías | E21: Lite | F21: 48 | G21: 48 | H21: 64 | I21: eliminado por ahora | J21: Nada | K21: =IFERROR(INDEX(G21:J21,MATCH($E21,Ediciones!$A$5:$A$8,0))*Leeme!$C$6,"") -> 480 | L21: Sin Delta | N21: no | O21: no | P21: no | Q21: sí | R21: Brand kit + HUBSALON-DESIGN.md | S21: ¿Reemplaza a Beauty o convive?
A22: web | B22: HUB Web | C22: Apps web a medida | E22: Lite | F22: 48 | G22: 48 | H22: 64 | I22: eliminado por ahora | J22: Nada | K22: =IFERROR(INDEX(G22:J22,MATCH($E22,Ediciones!$A$5:$A$8,0))*Leeme!$C$6,"") -> 480 | L22: Sin Delta | N22: no | O22: no | P22: sí | Q22: sí | R22: Estudio jun-2026 (proyecto + mantenimiento) | S22: Modelo distinto (proyecto + mantenimiento). ¿Va en Especiales o fuera del catálogo?

Sheet Add-ons
A1: Add-ons — se cobran aparte de la suscripción
A3: Add-on | B3: Lite | C3: Core | D3: Pro | E3: Enterprise | F3: Unidad | G3: Estado | H3: Fuente | I3: Decisión / nota
A4: Usuario adicional | B4: 5 | C4: 4 | D4: 3 | E4: 2 | F4: $/mes | G4: confirmado | H4: Catalog.php addons
A5: Dominio propio | B5: — | C5: — | D5: 5 | E5: Incluido | F5: $/mes | G5: propuesta | H5: Catalog.php addons | I5: Confirmar $5.
A6: Email saliente con tu dominio | B6: — | C6: — | D6: 5 | E6: Incluido | F6: $/mes | G6: propuesta | H6: Catalog.php addons | I6: Confirmar $5.
A7: Sucursal adicional | B7: — | C7: — | D7: — (5 incl.) | E7: 64 | F7: $/mes | G7: override en panel (Enterprise); pendiente Core/Pro | H7: JSON vivo Enterprise · estudio jun: $30 | I7: CATALOGO.md lo deja pendiente ('hoy se sube de edición'). ¿Core/Pro pueden comprar sucursal suelta? ¿$64 aplica solo Enterprise?
A8: PAC facturación electrónica | B8: cliente | C8: cliente | D8: cliente | E8: cliente | F8: — | G8: confirmado | H8: Catalog.php addons | I8: Lo paga el cliente directo al PAC; SuiteHub integra sin cobro.
A9: Setup / implementación (one-time) | F9: $ una vez | G9: NO EXISTE en catálogo vigente | H9: Estudio jun-2026: $100–500 (prom. $200) | I9: Decisión importante: el modelo actual no cobra implementación. Es ingreso real y filtra curiosos. ¿Se agrega?
A10: Capacitación on-site | F10: $ una vez | G10: no está | H10: Estudio jun-2026: $80 | I10: ¿Se ofrece?
A11: Gestión de certificado de firma electrónica | F11: $ una vez / 2 años | G11: no está | H11: Estudio jun-2026: $50 | I11: ¿Se ofrece?
A12: Terminal / estación KDS adicional | F12: $/mes | G12: no está | H12: Estudio jun-2026: $18 | I12: Relevante para Restaurant/POS. ¿Se cobra por terminal?
A13: HUB POS como módulo de caja sobre otro vertical | D13: 15 | E13: 15 | F13: $/mes | G13: propuesta | H13: CATALOGO.md Parte 4 | I13: Propuesta +$15/mes. Confirmar.

Sheet Especiales
A1: Casos especiales y modelos fuera de la matriz
A2: En el panel la lista 'especiales' está VACÍA. Aquí va todo lo que no encaja en Vertical × Edición.
A4: # | B4: Ítem | C4: Modelo | D4: $/mes | E4: $/año | F4: $/setup | G4: Estado | H4: Fuente | I4: Decisión / nota
A5: 1 | B5: HUB POS standalone (caja sola) | C5: fijo | D5: 36 | E5: =IF(ISNUMBER(D5),D5*Leeme!$C$6,"") -> 360 | G5: CONFLICTO | H5: CATALOGO.md: $36/mes ($360/año) 'confirmado' · Products.php: $48/$480 | I5: Dos precios vivos para lo mismo. La landing pública usa Products.php ($48). ¿$36 o $48?
A6: 2 | B6: HUB Traffic — setup de hardware | C6: cotizacion | E6: =IF(ISNUMBER(D6),D6*Leeme!$C$6,"") | G6: propuesta | H6: CATALOGO.md | I6: Cotización por # sensores/cámaras y local. Delta +$30/mes propuesto (grupo pesado = $36 en deltas).
A7: 3 | B7: HUB Web — app a medida | C7: desde | D7: 29 | E7: =IF(ISNUMBER(D7),D7*Leeme!$C$6,"") -> 290 | F7: 800 | G7: fuera de catálogo | H7: Estudio jun-2026: Básico $29+$800 · Pro $79+$2,500 · Premium $149+$5,000 | I7: ¿Se mantiene como línea de servicio de PROOQ (no SuiteHub)?
A8: 4 | B8: White-label / reventa | C8: cotizacion | E8: =IF(ISNUMBER(D8),D8*Leeme!$C$6,"") | G8: incluido en Enterprise | H8: Catalog.php Enterprise | I8: ¿Margen para distribuidores? Memoria dice canal mixto directo + distribuidores.
A9: 5 | B9: Integraciones custom / API dedicada | C9: cotizacion | E9: =IF(ISNUMBER(D9),D9*Leeme!$C$6,"") | G9: vacío en panel | H9: CLAUDE.md panel
A10: 6 | B10: Restaurantes — modelo mayo 2026 (licencia + mensualidad) | C10: fijo | E10: =IF(ISNUMBER(D10),D10*Leeme!$C$6,"") | G10: MODELO ANTERIOR | H10: Memoria: Kiosko $1,500+$59 · POS $3,800+$149 · Restaurante $5,500+$249 · sucursal +$1,500/$99 · pedidos web +$1,200/$39 | I10: ¿Se retira definitivamente? Si algún cliente lo compró así, documentar como legado.
A11: 7 | B11: Modelo de puntos ($12/pt) | C11: — | E11: =IF(ISNUMBER(D11),D11*Leeme!$C$6,"") | G11: MODELO ANTERIOR | H11: Memoria mayo 2026 | I11: ¿Retirar? Hoy nada en el panel usa puntos.

Sheet Conflictos
A1: Conflictos y huecos detectados — decidir uno por uno
A3: # | B3: Tema | C3: Fuente A dice | D3: Fuente B dice | E3: Impacto | F3: Decisión (Kenny)
A4: 1 | B4: HUB Restaurant Core | C4: Catalog.php (código): $48 (línea Core) | D4: Panel en vivo / JSON: $72 | E4: Landing, correo y sitio muestran $72; si se reinstala o revierte la BD cae a $48.
A5: 2 | B5: HUB POS standalone | C5: CATALOGO.md: $36/mes 'confirmado' | D5: Products.php + landing: $48/mes | E5: Precio público inconsistente entre docs y landing.
A6: 3 | B6: Qué significa 'Lite' | C6: Catálogo: edición de entrada $24 con FE DGI | D6: PRODUCTS.md/estudio: 'HubLite' producto micro sin FE / $19 | E6: El plan 2026 lo marca: 'Lite significa tres cosas'. Confunde ventas.
A7: 4 | B7: Sucursales Enterprise | C7: Catalog.php: ilimitadas | D7: JSON vivo: 1 principal + $64/mes adicional | E7: Cambia la promesa Enterprise.
A8: 5 | B8: Boutique y Market | C8: No existen en Catalog.php defaults() | D8: Existen en JSON vivo (override BD) y Products.php | E8: Viven solo en la BD del servidor. Riesgo de pérdida; no están en tests.
A9: 6 | B9: Beauty vs Salon | C9: Catálogo: HUB Beauty | D9: Brand kit: hub-salon-logo, HUBSALON-DESIGN.md | E9: Dos nombres para el mismo vertical.
A10: 7 | B10: Setup / implementación | C10: Catálogo vigente: no se cobra | D10: Estudio jun-2026: $100–500 one-time (prom. $200), ~40% del ingreso año 1 en su proyección | E10: Renunciar a setup baja el ticket inicial y sube churn temprano (según el mismo estudio).
A11: 8 | B11: Descuento anual | C11: Catálogo: ×10 (≈16.7%) | D11: Estudio jun-2026: ×12×0.9 (10%) | E11: Ya resuelto a ×10 en panel; el estudio quedó viejo. | F11: Confirmado ×10 (asumido)
A12: 9 | B12: Entidad en materiales | C12: JSON meta y sitio: 'PROOQ LLC (USA) · operado en Panamá por PROOQ S.A.' | D12: Decisión sep-2026: S.A. = Panamá, LLC = EE.UU. (pares por territorio) | E12: Cambia footer, privacidad, términos, meta del catálogo y PRODUCTS.md/README de marca.
A13: 10 | B13: HUB Time | C13: Brand kit ago-2026: badge, logo, favicons, preview | D13: No existe en catálogo, JSON ni Products.php | E13: Producto sin definición comercial.
A14: 11 | B14: Deltas de módulo | C14: Catalog.php: $12/$24/$36 por grupo | D14: No existe catálogo de módulos que los use | E14: Número sin producto detrás. ¿Se retira hasta tener módulos?
A15: 12 | B15: Modelos anteriores (puntos, licencia restaurantes) | C15: Memoria mayo-2026 | D15: Nada en panel los usa | E15: Ruido en materiales viejos (brochures, pitches).

Sheet Historial
A1: Historial de modelos de precio (para no volver a mezclarlos)
A3: Cuándo | B3: Modelo | C3: Descripción | D3: Estado
A4: may-2026 | B4: Puntos + licencia | C4: Precios en puntos ($12/pt), público en balboas. Restaurantes con pago inicial + mensualidad (Kiosko/POS/Restaurante). Canal directo + distribuidores. | D4: Anterior — retirar salvo clientes legado
A5: jun-2026 (estudio) | B5: 3 planes por producto + setup | C5: HubPOS $29/59/99, HubRestaurant $49/89/149, HubBoutique $39/79/129, HubCore $19/45/89, HubWeb $29/79/149 + proyecto. Setup $100–500. Anual −10%. | D5: Anterior — sirve como referencia de mercado
A6: 2026-06-25 | B6: Ediciones × Verticales (vigente) | C6: Lite $24 / Core $48 / Pro $96 / Enterprise $192. Verticales en línea de edición sin recargo, salvo precio propio. Anual ×10. Add-ons aparte. PAC lo paga el cliente. | D6: VIGENTE — fuente: panel
A7: 2026-08-02 | B7: Overrides en panel | C7: Restaurant Core $72, Enterprise sucursal +$64, Boutique y Market agregados. | D7: Vigente en vivo, no en código
